odoo/addons/sale_order_split_strategy/README.rst
odoo/addons/sale_order_split_strategy/__init__.py
odoo/addons/sale_order_split_strategy/__manifest__.py
odoo/addons/sale_order_split_strategy/i18n/it.po
odoo/addons/sale_order_split_strategy/i18n/sale_order_split_strategy.pot
odoo/addons/sale_order_split_strategy/models/__init__.py
odoo/addons/sale_order_split_strategy/models/sale_order.py
odoo/addons/sale_order_split_strategy/models/sale_order_split_strategy.py
odoo/addons/sale_order_split_strategy/readme/CONFIGURE.rst
odoo/addons/sale_order_split_strategy/readme/CONSTRIBUTORS.rst
odoo/addons/sale_order_split_strategy/readme/DESCRIPTION.rst
odoo/addons/sale_order_split_strategy/security/ir.model.access.csv
odoo/addons/sale_order_split_strategy/static/description/icon.png
odoo/addons/sale_order_split_strategy/static/description/index.html
odoo/addons/sale_order_split_strategy/tests/__init__.py
odoo/addons/sale_order_split_strategy/tests/test_split_strategy.py
odoo/addons/sale_order_split_strategy/views/mail_message_template.xml
odoo/addons/sale_order_split_strategy/views/sale_order.xml
odoo/addons/sale_order_split_strategy/views/sale_order_split_strategy.xml
odoo14_addon_sale_order_split_strategy-14.0.1.0.1.dev6.dist-info/METADATA
odoo14_addon_sale_order_split_strategy-14.0.1.0.1.dev6.dist-info/WHEEL
odoo14_addon_sale_order_split_strategy-14.0.1.0.1.dev6.dist-info/top_level.txt
odoo14_addon_sale_order_split_strategy-14.0.1.0.1.dev6.dist-info/RECORD
