Metadata-Version: 2.1
Name: odoo14-addon-sale_order_split_strategy
Version: 14.0.1.0.1.dev6
Summary: Define strategies to split sales orders
Home-page: https://github.com/OCA/sale-workflow
Author: Camptocamp, Odoo Community Association (OCA)
Author-email: support@odoo-community.org
License: AGPL-3
Classifier: Programming Language :: Python
Classifier: Framework :: Odoo
Classifier: Framework :: Odoo :: 14.0
Classifier: License :: OSI Approved :: GNU Affero General Public License v3
Classifier: Development Status :: 3 - Alpha
Requires-Python: >=3.6
Requires-Dist: odoo<14.1dev,>=14.0a
